dtpyenv/__init__.py
dtpyenv/env.py
dtpyenv-1.0.0.dist-info/METADATA
dtpyenv-1.0.0.dist-info/WHEEL
dtpyenv-1.0.0.dist-info/RECORD
