Metadata-Version: 2.3
Name: dtpyenv
Version: 1.0.0
Summary: A light python package for managing environment variables.
License: MIT
Author: Reza Shirazi
Author-email: reza@datgate.com
Requires-Python: >=3.11.9,<3.12.0
Classifier: License :: OSI Approved :: MIT License
Classifier: Programming Language :: Python :: 3
